arcane/bing/__init__.py
arcane/bing/client.py
arcane/bing/exceptions.py
arcane/bing/helpers.py
arcane/bing/types.py
arcane_bing-0.5.1.dist-info/METADATA
arcane_bing-0.5.1.dist-info/WHEEL
arcane_bing-0.5.1.dist-info/RECORD
